disconn/__init__.py
disconn/bot.py
disconn-0.0.1.dist-info/LICENSE
disconn-0.0.1.dist-info/METADATA
disconn-0.0.1.dist-info/WHEEL
disconn-0.0.1.dist-info/top_level.txt
disconn-0.0.1.dist-info/RECORD
