Metadata-Version: 2.1
Name: disconn
Version: 0.0.1
Summary: A python wrapper for making discord bots
Author: disconn development
Classifier: Programming Language :: Python :: 3
Classifier: License :: OSI Approved :: MIT License
Classifier: Operating System :: OS Independent
Requires-Python: >=3.10
License-File: LICENSE
